SBPPhysicsEqResistance/SBPPhysicsEqResistance.py
SBPPhysicsEqResistance/__init__.py
SBPPhysicsEqResistance-0.0.3.dist-info/LICENSE
SBPPhysicsEqResistance-0.0.3.dist-info/METADATA
SBPPhysicsEqResistance-0.0.3.dist-info/WHEEL
SBPPhysicsEqResistance-0.0.3.dist-info/top_level.txt
SBPPhysicsEqResistance-0.0.3.dist-info/RECORD
