Metadata-Version: 2.1
Name: SBPPhysicsEqResistance
Version: 0.0.3
Summary: A scientific package to find equivalent resistance in physics
Home-page: UNKNOWN
Author: Mohammad Ghiasvand Mohammadkhani
Author-email: mohammadmohammadkhani82@gmail.com
License: UNKNOWN
Keywords: "Science By Programming","Physics","Python","Find equivalent resistance"
Platform: UNKNOWN
Classifier: Programming Language :: Python :: 3
Classifier: License :: OSI Approved :: MIT License
Classifier: Operating System :: OS Independent
Requires-Python: >=3.6
License-File: LICENSE
